{
    "common": {
        "tableNameInChinese": "",
        "tableNameInPortuguese": "",
        "taskNameInChinese": "",
        "taskNameInPortuguese": "",
        "taskNamePlaceholder": "",
        "pwTaskNamePlaceholder": "",
        "tableNamePlaceholder": "",
        "pwTableNamePlaceholder": "",
        "specialWork": "",
        "query": "Consultar",
        "tabulationUnit": "",
        "previousPage": "",
        "nextPage": "",
        "select": "Seleccionar",
        "selectSpace": "選 擇",
        "form": "",
        "selectForm": "",
        "none": "",
        "everyday": "",
        "weekly": "",
        "monthly": "",
        "annually": "",
        "dailyReport": "",
        "weeklyReport": "",
        "monthlyReport": "",
        "quarterlyReport": "",
        "annualReport": "",
        "disposable": "",
        "one": "",
        "two": "",
        "three": "",
        "four": "",
        "five": "",
        "six": "",
        "seven": "",
        "monday": "",
        "tuesday": "",
        "wednesday": "",
        "thursday": "",
        "friday": "",
        "saturday": "",
        "sunday": "",
        "distributeDailyTasksForTheDay": "",
        "immediatelyIssueTheNextTask": "",
        "issueNextTaskPerHour": "",
        "tianxiaIssuesTheNextTask": "",
        "issueNextTaskOnAWeeklyBasis": "",
        "issueTheNextTaskOnTheDayOfEachMonth": "",
        "immediatelyIssueTasks": "",
        "workDay": "",
        "natureDay": "",
        "submitBeforeEachSubmission": "",
        "submitOnceAWeekBeforeEachWeek": "",
        "submitBeforeTheDayOfEachMonth": "",
        "lastSubmissionPerMonth": "",
        "whatIsTheDeadlineForSubmissionEveryMonth": "",
        "thisYear": "Corrente ano",
        "onWhatMonth": "",
        "whenShouldISubmitThisFormAndSubmitItOnce": "",
        "whenDidYouSubmitThisForm": "",
        "confirmToDeleteTheTaskSchedule": "",
        "tips": "Lembrete",
        "confirm": "Confirmar",
        "confirmSpace": "確 定",
        "cancel": "Cancelar",
        "cancelSpace": "取 消",
        "operation": "Operação",
        "modify": "Alterar",
        "delete": "Apagar",
        "serialNumber": "N煤mero de ordem",
        "reportingDepartmentAndOrganization": "",
        "assignTasksByTheCoordinationRoom": "",
        "doYouHaveACoordinatingRoomRole": "",
        "reportingUnitLevel": "",
        "reportingUnitLevelPlaceholder": "",
        "subordinateUnits": "",
        "unitOfTheSameLevel": "",
        "subordinateAndPeerUnits": "",
        "selectUnit": "",
        "confirmDeletion": "Confirmar a eliminação",
        "enterKeywordsForFiltering": "",
        "selectReportingUnit": "",
        "reportingUnit": "",
        "reportingUnitCode": "",
        "reportingUnitPlaceholder": "",
        "theReportingUnitHasNotBeenSelectedYet": "",
        "complete": "",
        "onlyReportInTheReportingSystem": "",
        "mustBeSubmittedSimultaneouslyThroughOtherChannels": "",
        "paperFormsNeedToBeCollected": "",
        "itNeedsToBeSubmittedSimultaneouslyOnThe": "",
        "itNeedsToBeSubmittedSimultaneouslyOnTheGuangdongPoliticalExchange": "",
        "mustBeSubmittedSimultaneouslyThroughOtherChannels1": "",
        "multipleReportingSituations": "",
        "taskPlan": "",
        "taskStatus": "",
        "tableStatus": "",
        "distributionStatus": "",
        "deadlineForReporting": "",
        "deadlineForReportingPlaceholder": "",
        "pleaseSelect": "Seleccione",
        "selectAll": "",
        "education": "Ensino",
        "healthcare": "",
        "civilAffairs": "",
        "publicSafety": "",
        "other": "Outros",
        "zoning": "",
        "startReportingTime": "",
        "category": "",
        "categoryPlaceholder": "",
        "collect": "",
        "collectTasks": "",
        "toBeCollected": "",
        "completed": "Proj concluído",
        "toBeCompleted": "",
        "inUse": "",
        "guangdongProvince": "",
        "underExecution": "",
        "revoked": "",
        "toBeFilledIn": "",
        "reportOnADailyBasis": "",
        "reportByWeek": "",
        "monthlyReporting": "",
        "reportByQuarter": "",
        "reportByYear": "",
        "oneTimeReporting": "",
        "epidemicPreventionAndControl": "",
        "enterpriseResumptionOfWorkAndProduction": "",
        "yes": "Sim",
        "no": "Não",
        "see": "Consultar",
        "fillInTheReport": "",
        "detail": "Detalhes",
        "tempApprove": "",
        "receivedSuccessfully": "",
        "collectionFailed1": "",
        "listOfFormsToBeCollected": "",
        "putAway": "",
        "expand": "",
        "releaseTime": "",
        "stamped": "",
        "toBeStamped": "",
        "sealToBeAppliedFor": "",
        "noNeedToStamp": "",
        "industrySector": "",
        "reportingPeriod": "",
        "applicationSignatureTime": "",
        "applicant": "",
        "signatureStatus": "",
        "signatureToBeAppliedFor": "",
        "toBeSigned": "",
        "signed": "",
        "noSignatureRequired": "",
        "workOrderValidity": "",
        "auditStatus": "",
        "reasonDescription": "",
        "enable": "Activar",
        "enabled": "Activado",
        "deactivate": "Desactivar",
        "deactivated": "Inutilizado",
        "reported": "",
        "received": "",
        "completedButNotReported": "",
        "pendingReview": "",
        "by": "Aprovação",
        "notPassed": "Reprovação",
        "all": "Totalidade",
        "toBeDistributed": "",
        "distributed": "",
        "listOfFormsToBeStamped": "",
        "issuingUnit": "",
        "listOfFormsToBeSigned": "",
        "approved": "審覈通過",
        "reviewFailed": "審覈不通過",
        "howManyRecordsInTotal": "",
        "taskProgress": "",
        "completingTasks": "",
        "fillInDetails": "",
        "more": "Mais",
        "reopenTask": "",
        "exportDetails": "",
        "downloadAttachments": "",
        "exportSummaryTable": "",
        "exportSignatureFile": "",
        "return": "Voltar",
        "summaryTable": "",
        "remittanceTable": "",
        "filterTheNameOfTheReportingUnitPlaceholder": "",
        "reportingDepartmentAndOrganization1": "",
        "finishTask1": "",
        "finishTask2": "",
        "taskCompleted": "",
        "collectionFailed": "",
        "collecting": "",
        "serverError": "",
        "afterCollectionTip": "",
        "thereAreCurrentlyNoDownloadableAttachmentsAvailable": "",
        "reportedButNotCollectedTip": "",
        "requestingExtension": "",
        "exportTableImageCompressionPackage": "",
        "expandingAndGeneratingAttachments": "",
        "expandingAndGeneratingASchedule": "",
        "exportingSignatureFile": "",
        "downloadSignatureFiles": "",
        "exportingTip": "",
        "exportingDetailsList": "",
        "typeOfReportingCycle": "",
        "typeOfReportingCyclePlaceholder": "",
        "loading": "",
        "submitForReview": "",
        "review": "",
        "fillOutTheForm": "",
        "fillInTheAttachmentOfTheForm": "",
        "submittedToTheFinanceBureau": "",
        "withdraw": "",
        "signatureInformation": "",
        "submissionOfInformation": "",
        "reportingPrompt": "",
        "reportingPromptContent": "",
        "fillOutTheFormFirst": "",
        "continueReporting": "",
        "uploadAttachments": "Upload anexos",
        "uploaderName": "",
        "attachmentName": "Designação de anexos",
        "remark": "Observação",
        "uploadTime": "Hora do upload",
        "download": "Download",
        "signedInformation": "",
        "pleaseSelectAnElectronicSignature": "",
        "taskRecord": "",
        "theCurrentTableIsLocked": "",
        "close": "Fechar",
        "submitAndSubmitDataForReview": "",
        "currentlyReportedAsAnEmptyTableTip": "",
        "fillingInstructions": "",
        "fillingInstructionsPlaceholder": "",
        "reportedBy": "",
        "reportedByPlaceholder": "",
        "contactInformation": "",
        "contactInformationPlaceholder": "",
        "attachmentInformation": "",
        "reviewOfFillingInData": "",
        "clickOnTheFileNameToDownload": "",
        "fileTypeDoesNotSupportPreview": "",
        "pleaseEnterTheReviewCommentsBelow": "",
        "reviewComments": "",
        "reviewCommentsPlaceholder": "",
        "approved1": "",
        "noDataReportedTip": "",
        "pleaseChooseNotToFillInTheReason": "",
        "thereIsNoSituationForThisTask": "",
        "reasonForIncompleteFilling": "",
        "continueToSubmit": "",
        "continueFillingOutTheForm": "",
        "assignFillingTasks": "",
        "receivedCommentsCannotBeEmpty": "",
        "commentDescriptionCannotBeEmpty": "",
        "export": "Exportar",
        "exportExcel": "Exportar ficheiro do excel",
        "pleaseImproveTheReason": "",
        "assignReportingTasks": "",
        "uploadTip": "",
        "uploadTip1": "",
        "confirmDeleteFileTip": "",
        "noDataReportedTip1": "",
        "theCurrentTableIsInvalid": "",
        "areYouSureYouWantToContinueFillingOutTheForm": "",
        "downloadFileFailed": "",
        "theCurrentFormIsNotSignedOrStamped": "",
        "redMarkedAsRequired": "",
        "failedToObtainDetailedDataForFillingInTheReport": "",
        "singleTableCurrentlyDoesNotSupportSharingExternally": "",
        "submittedSuccessfully": "",
        "operationFailed": "",
        "auditSuccessful": "",
        "configurationMissingComparison": "",
        "submissionInstructions": "",
        "submitAttachments": "",
        "attemptingToLoadControl": "",
        "viewingPageDoesNotSupportCallingPreviousCycleData": "",
        "permissionToFillInTheForm": "",
        "pleaseEnterYourName": "",
        "selectPersonnel": "",
        "filledBy": "",
        "followTheCurrentAllocationSettings": "",
        "cancelledBy": "",
        "joinedBy": "",
        "reportingAuthority": "",
        "reportedBy1": "",
        "cancelTheSubmitter": "",
        "joinTheReporter": "",
        "shareExternal": "",
        "sharedBy": "",
        "cancelSharedBy": "",
        "joinTheSharer": "",
        "auditPermissions": "審覈權限",
        "reviewedBy": "審覈人",
        "cancelReviewer": "取消審覈人",
        "joinReviewer": "",
        "reset": "Reiniciar",
        "shareExternalSettings": "",
        "auditPermissionSettings": "",
        "update": "Actualizar",
        "confirm1": "Confirmar",
        "pleaseAssignTheSubmitter": "",
        "pleaseAssignAPersonToFillOutTheForm": "",
        "pleaseAssignReviewers": "",
        "pleaseAssignASharer": "",
        "operationSuccess": "",
        "operationFailed1": "",
        "pleaseSelectTheFillingPerson": "",
        "pleaseSelectTheReportingPerson": "",
        "pleaseSelectReviewer": "",
        "pleaseSelectASharer": "",
        "signatureDocument": "",
        "downloadSignatureFiles1": "",
        "applicationInformation": "",
        "sealedBy": "",
        "sealedByPlaceholder": "",
        "applicationTime": "Tempo de pedido",
        "reasonForApplication": "",
        "approvalInformation": "",
        "approvalResults": "",
        "returnStampApplication": "",
        "agreeToApply": "",
        "approvalTime": "",
        "sealInformation": "",
        "certifiedPhoto": "",
        "sealType": "",
        "institution": "Organismo",
        "individual": "",
        "sealNumber": "",
        "certificateName": "",
        "stampedOn": "",
        "isTheCurrentSealValid": "",
        "stampPreview": "",
        "sealName": "",
        "sealVersion": "",
        "sealCode": "",
        "sealCode1": "",
        "digitalCertificateSerialNumber": "",
        "returnRestatement": "",
        "withdrawalOfRestatement": "",
        "collectionForm": "",
        "dataPeriod": "",
        "reviewComments1": " 審覈通過，審覈意見：",
        "reviewComments2": " 審覈不通過，審覈意見：",
        "infoHtmlText1": "",
        "infoHtmlText2": "",
        "infoHtmlText3": "",
        "infoHtmlText4": "",
        "infoHtmlText5": "",
        "infoHtmlText6": "",
        "reasonDescriptionPlaceholder": "",
        "reasonForWithdrawal": "",
        "theInformationFilledInHasBeenWithdrawn": "",
        "reasonForReturn": "Motivo da devolução",
        "theInformationFilledInHasBeenReturned": "",
        "confirmRemoval": "",
        "onlyOneFileCanBeUploaded": "",
        "applicationSeal": "",
        "withdrawalOfSealApplication": "",
        "stamp": "",
        "restamping": "",
        "reasonForStamping": "",
        "reasonForStampingPlaceholder": "",
        "submitApplication": "",
        "sealApplicationAcceptance": "",
        "userId": "",
        "userIdPlaceholder1": "",
        "userIdPlaceholder": "",
        "usingASeal": "",
        "usingASealPlaceholder": "",
        "sealPin": "",
        "sealPinPlaceholder": "",
        "agreeToStamp": "",
        "selectSignature": "",
        "reviewCommentsPlaceholder1": "請選擇審覈意見",
        "reviewCommentsOption1": "",
        "reviewCommentsOption2": "",
        "reviewCommentsOption3": "",
        "reviewCommentsOption4": "自定義審覈意見，請直接上報",
        "customComments": "",
        "customCommentsPlaceholder": "請填寫自定義審覈意見",
        "returnApplication": "",
        "pleaseFillInTheApplicationInformation": "",
        "sealApplyReasonTip": "",
        "pleaseSelectASeal": "",
        "pleaseEnterACustomReviewOpinion": "請輸入自定義審覈意見",
        "stampApplicationInformation": "",
        "returnStampedApplicationInformation": "",
        "successfullyApplied": "",
        "confirmWithdrawalOfSealApplication": "",
        "afterTaskSubmission": "",
        "contactAdministratorTip1": "",
        "contactAdministratorTip2": "",
        "applicationSignature": "",
        "withdrawalOfSignatureRequest": "",
        "viewSignatureInformation": "",
        "abandonSignature": "",
        "signature": "",
        "selectSignatory": "",
        "pleaseEnter": "",
        "electronicSignaturesRequireRealNameAuthentication": "",
        "realName": "Nome verdadeiro",
        "idNumber": "",
        "generateQrCodeForYuexinSignature": "",
        "reasonForApplication1": "",
        "scanTheQrCode": "",
        "tips1": "提示：<br><span style='color: #F56C6C'>完成簽名前，請勿關閉彈窗<br>在粵信籤小程序完成簽名後，方可點擊下方的“完成簽名”按鈕！</span>",
        "completeSignature": "",
        "reasonForAbandonment": "",
        "signatureInformation1": "",
        "signatureFile": "",
        "downloadSignatureFile": "",
        "signInfo1": "",
        "signInfo2": "",
        "signInfo3": "",
        "signInfo4": "",
        "signInfo5": "",
        "signInfo6": "",
        "autographTitle1": "",
        "autographTitle2": "",
        "incorrectFormatOfIdCard": "",
        "signApplyReason": "",
        "pleaseSelectASignatory": "",
        "pleaseFillInTheApplicationReason": "",
        "pleaseFillInYourRealName": "",
        "pleaseFillInYourIdNumber": "",
        "pleaseFillInTheReasonForAbandonment": "",
        "confirmWithdrawalOfSignatureRequest": "",
        "recallSuccessful": "",
        "recallFailed": "",
        "computerSide": "",
        "failedToCreateOrder": "",
        "finishSignTip": "",
        "taskDistribution": "",
        "taskAssignment": "",
        "taskForwarding": "",
        "fillOutTheFormAndSubmitIt": "",
        "returnForm": "",
        "recallTable": "",
        "thereAreCurrentlyNoRecordsAvailableDot": "",
        "fileUploadInProgress": "",
        "reportingDetails": "",
        "reporting": "",
        "reportingData": "",
        "submit": "Apresentar",
        "submitData": "",
        "submitter": "",
        "reportAttachments": "",
        "reportAttachmentsTip": "",
        "reportAttachmentsRemarks": "",
        "attachments": "Anexos",
        "pleaseEnterTheCorrectPhoneNumber": "",
        "indicatorForwardingToSubordinates": "",
        "indicatorAllocation": "",
        "internalAllocation": "",
        "pleaseEnterTheSubmitter": "",
        "preReportingInspectionPrompt1": "",
        "preReportingInspectionPrompt2": "",
        "preReportingInspectionPrompt3": "",
        "preReportingInspectionPrompt4": "",
        "preReportingInspectionPrompt5": "",
        "preReportingInspectionPrompt6": "",
        "preReportingInspectionPrompt7": "",
        "preReportingInspectionPrompt8": "",
        "tips2": "",
        "tips3": "",
        "tips4": "",
        "tips5": "",
        "tips6": "",
        "pleaseBePatientAndWaitDot": "",
        "successfullyReported": "",
        "contactDevelopers": "",
        "fileUploadPrompt1": "",
        "fileUploadPrompt2": "",
        "fileUploadPrompt3": "",
        "fileUploadPrompt4": "",
        "fileUploadPrompt5": "",
        "fileUploadPrompt6": "",
        "sharingSettings": "",
        "setEndTime": "",
        "to": "",
        "startDate": "",
        "endDate": "",
        "sharingSettingsTip1": "",
        "sharingSettingsTip2": "",
        "sharingSettingsTip3": "",
        "sharingSettingsTip4": "",
        "sharingSettingsTip5": "",
        "shareWith": "",
        "sharingMethod": "",
        "chooseAChannel": "",
        "chooseAChannelPlaceholder": "",
        "shareLink": "",
        "copy": "",
        "shareQrCode": "",
        "confirmSharing": "",
        "theTableOfContentsDoesNotAllowSharing": "",
        "successfullyShared": "",
        "sharingFailed": "",
        "successfullyCopied": "",
        "fileUploadPrompt7": "",
        "submissionInstructionsPlaceholder": "",
        "nameAndContactPhoneNumberOfTheSubmitter": "",
        "nameAndContactPhoneNumberOfTheSubmitterPlaceholder": "",
        "electronicSignature": "",
        "inTheSignatureAndSealDot": "",
        "submitting": "",
        "submission": "",
        "tableReportingStatus": "",
        "reportType1": "",
        "reportType2": "",
        "reportTypeInfos1": "",
        "reportTypeInfos2": "",
        "reportTypeInfos3": "",
        "reportTypeInfos4": "",
        "returnSpace": "",
        "pleaseSelectTheAttachmentThatNeedsToBeUploaded": "",
        "multipleReportingSituationsPlaceholder": "",
        "noSignatureRequired1": "",
        "catalogName": "",
        "successfullySubmitted": "",
        "save": "Gravar",
        "auxiliaryFunctions": "",
        "costTaskIndicator": "",
        "exportIndicatorTemplate": "",
        "importTable": "",
        "importCollectedData": "",
        "dataItemReuseFeedback": "",
        "initiateFeedback": "",
        "viewFeedback": "",
        "reportingPeriod1": "",
        "fillingRequirements": "",
        "allocationIndicators": "",
        "splitMetrics": "",
        "importIndicatorTemplatePopup": "",
        "loadingControlsDot": "",
        "exportIndicatorReminder": "",
        "errorReadingData": "",
        "noDataItemsBound": "",
        "theDataFilledInHasBeenAutomaticallySaved": "",
        "dataSavedSuccessfully": "",
        "failedToSaveData": "",
        "incorrectFormatInFillingOutTheForm": "",
        "configurationErrorTip1": "",
        "configurationErrorTip2": "",
        "loadingData": "",
        "incorrectFormatInFillingOutTheFormTip": "",
        "incorrectFormatInFillingOutTheFormTip1": "",
        "loadingData1": "",
        "importPrompt": "",
        "importFailed": "",
        "noCollectedData": "",
        "importSuccessful": "",
        "importIndicatorReminder": "",
        "fillingInData": "",
        "clearReportingPerson": "",
        "deadlineForFillingInTheReport": "",
        "specificDate": "",
        "showAllTablesForThisTask": "",
        "tableName": "",
        "fillInBatch": "",
        "fillInTheDeadlineForSubmission": "",
        "automaticDistribution": "",
        "manualDistribution": "",
        "oneReportPerDay": "",
        "fillInTheReportEveryMonday": "",
        "reportOnJanuarySt": "",
        "fillInAndReportOnAQuarterlyBasis": "",
        "reportOnceAYear": "",
        "reportOnlyOnce": "",
        "distributeTasks": "",
        "startFillingDate": "",
        "distribution": "",
        "successfullyDistributed": "",
        "distributionFailurePrompt": "",
        "doIHaveToSubmitAttachments": "",
        "departmentalInstitutions": "Serviço e organismo",
        "departmentalInstitutionsPlaceholder": "",
        "departmentOrganizationNumber": "Nº de serviço e organismo",
        "cnDepartmentalInstitutions": "",
        "ptDepartmentalInstitutions": "",
        "departmentAndInstitutionAbbreviation": "Sigla do serviço/organismo",
        "submissionTime": "",
        "collectionTime": "",
        "lastUpdateTime": "Tempo de última actualização",
        "reportedForCollection": "",
        "specialInstructions": "",
        "emptyTableReporting": "",
        "sendingFailedColon": "",
        "successfullySentColon": "",
        "reminderForReporting": "",
        "reminder": "",
        "missingInterfaceRequestParameters": "",
        "reminderForReportingTip": "",
        "reminderForReportingTip1": "",
        "reminderForReportingTip2": "",
        "reminderForReportingTip3": "",
        "reminderForReportingTip4": "",
        "reminderForReportingTip5": "",
        "return1": "Devolver",
        "returnFailed": "",
        "summarizeData": "",
        "stopSending": "",
        "stopSendingPrompt": "",
        "stopSendingPrompt1": "",
        "stopSendingPrompt2": "",
        "stopSendingPrompt3": "",
        "stopSendingPrompt4": "",
        "reasonForChange": "Motivo da alteração",
        "reasonForChangePlaceholder": "",
        "taskEnd": "",
        "taskInterruption": "",
        "taskCancellation": "",
        "pleaseSelectTheReasonForStoppingTheShipment": "",
        "smsNotificationPrompt1": "",
        "smsNotificationPrompt2": "",
        "smsNotificationPrompt3": "",
        "sendSms": "",
        "continueSending": "",
        "sendingReminderMessageIsCurrentlyBeingSent": "",
        "contactAdministrator": "",
        "supervisionReminderHasBeenSent": "",
        "stoppedSending": "",
        "reasonForChangeTip": "",
        "taskEnabledSuccessfully": "",
        "taskStoppedSuccessfully": "",
        "taskActivationFailed": "",
        "taskStopFailed": "",
        "modifyTheReportingDepartmentAndOrganization": "",
        "currentLevelUnit": "",
        "distributeToIndustryDepartments": "",
        "distributeToIndustryDepartmentsPlaceholder": "",
        "cnDepartmentName": "",
        "ptDepartmentName": "",
        "departmentAbbreviation": "Sigla do serviço",
        "departmentNature": "Natureza orgânica",
        "modifyReportingUnit": "",
        "currentlySelected": "",
        "reportingUnits": "",
        "joiningTheReportingUnit": "",
        "cancelReportingUnit": "",
        "theReportingUnitHasBeenSelected": "",
        "modificationOfReportingUnitTip": "",
        "modificationSucceeded": "",
        "theIssuingDepartmentCannotBeEmpty": "",
        "theReportingUnitCannotBeBlank": "",
        "viewSummaryData": "",
        "summarized": "",
        "deadlineForReporting1": "Data limite para comunicação ao superior",
        "status": "Estado",
        "completionTime": "",
        "thereIsUncollectedData": "",
        "dataCollected": "",
        "batchExport": "",
        "pleaseSpecifyThePeriodForExportingDataFirst": "",
        "exportingPleaseWait": "",
        "theTaskFillingUnitHasNotYetReportedAnyData": ""
    },
    "login": {
        "userName": "Utilizador",
        "password": "Senha",
        "login": "",
        "logining": ""
    },
    "task_web_manage_next_task_create": {
        "titleName": "",
        "basicInformation": "",
        "category": "",
        "categoryPlaceholder": "",
        "theTaskPlanHasNotBeenAddedYet": "",
        "theFormHasNotBeenSelectedYet": "",
        "note": "",
        "create": "",
        "cancel": "Cancelar",
        "successfullyDistributed": "",
        "distributionFailed": "",
        "components": {
            "baseInfo": {
                "taskName": "",
                "chinese": "",
                "taskNamePlaceholder": "",
                "taskNamePlaceholder1": "",
                "portuguese": "Português",
                "pwTaskNamePlaceholder": "",
                "sendDeptDivision": "",
                "sendDept": "",
                "taskPlan": "",
                "addPlan": "",
                "serialNumber": "N煤mero de ordem",
                "planType": "",
                "deadlineForSubmission": "",
                "taskIssuanceTime": "",
                "firstDeadlineForFillingIn": "",
                "planDescription": "",
                "operation": "Operação",
                "modify": "Alterar",
                "delete": "Apagar",
                "taskCycleType": "",
                "taskCycleTypePlaceholder": "",
                "taskStartTime": "",
                "taskStartTimePlaceholder": "",
                "taskStartTimePlaceholder1": "",
                "deadlineForReporting": "",
                "deadlineForReportingPlaceholder": "",
                "deadlineForReportingPlaceholder1": "",
                "deadlineForFillingInTheCycle": "",
                "eachQuarterOfThe": "",
                "monthOrdinalOfEachQuarter": "",
                "select": "Seleccionar",
                "front": "",
                "explanation": "Descrição",
                "contactPersonAndPhoneNumber": "",
                "contactPersonAndPhoneNumberPlaceholder": "",
                "contactPersonAndPhoneNumberPlaceholder1": "",
                "requirementsForSubmittingAttachments": "",
                "requirementsForSubmittingAttachmentsPlaceholder": "",
                "note": "",
                "doYouNeedToUploadAttachmentsForReporting": "",
                "yes": "Sim",
                "no": "Não",
                "ifYouChooseYes": "",
                "ifYouChooseNo": "",
                "attachmentType": "",
                "includingPictures": "",
                "withoutPictures": "",
                "allowUploadFormats": "",
                "doesItSupportUploadingMultipleCopies": "",
                "upTo5": "",
                "upTo50": "",
                "share": "",
                "uploadSizeLimit": "",
                "descriptionInfo": "截止填報時間：指在每一個週期內，填報部門必須在指定時間期限前完成數據填報任務。\n\n如：\n\n① 當任務週期類型爲：按日填報，截止填報時間爲：每日23時59秒59分時\n\n 則，填報單位應當在每日23時59分59秒前完成數據填報任務。",
                "taskDistributionMethodPlaceholder": "",
                "firstStatisticalTimeRangeIntervalPlaceholder": "",
                "theNumberOfUploadedFilesCannotBeEmpty": "",
                "theUploadSizeLimitCannotBeEmpty": ""
            },
            "taskCycleEditor": {
                "selectPlanType": "",
                "eachPiecesSubmitOnce": "",
                "everyTimePreviousSubmission": "",
                "everyMonthPreviousSubmission": "",
                "byTheLastDayOfEachMonthSubmission": "",
                "monthlyFirstFewSubmission": "",
                "xuhao1": "（1）",
                "xuhao2": "（2）",
                "xuhao3": "（3）",
                "everyDaydistributeTasks": "",
                "taskDistributionTimePlaceholder": "",
                "taskDistributionTimePlaceholder1": "",
                "howMany": "",
                "theFirstTaskToBeFilledInIs": "",
                "planDescription5": "",
                "noSpecialRequirements": "",
                "weeklyReport1": "",
                "aFew": "",
                "weeklyReport3": "",
                "reportingTimeLastMonth": "",
                "reportingTimeOfTheMonth": "",
                "issuedUnderTheMandate": "",
                "monthlyReport3": "（3）每月報送；",
                "monthlyReport1": "",
                "everyFewMonthSent": "（3）逢{frequencyVal}月報送；",
                "everyFewMonthSent1": "",
                "forwardDirectedMessageTable": "",
                "setImmediatelyAfterTheFollowingTasks": "",
                "report3": "",
                "planDescription3": "",
                "theFirstReportedTaskOfTheTime": "",
                "howManyWeeklyReports": "",
                "pleaseSelectAtLeastTwoMonthsOrMoreForTheMonthlyReport": "",
                "howManyHoursBeforeTheDeadlineToIssueTheNextTask": "",
                "howManyDaysBeforeTheDeadlineToSendTheNextTask": ""
            },
            "listSelect": {
                "daily": "",
                "weekly": "",
                "monthly": "",
                "quarterly": "",
                "yearly": ""
            },
            "fillUnit": {
                "ifAllUsersAreClosed": "",
                "selectTheReportingDepartmentAndOrganization": "",
                "joiningTheReportingDepartmentAndOrganization": "",
                "cancelFillingInDepartmentAndOrganization": "",
                "deleteCommonUnits": "",
                "selectedUnitInformation": ""
            },
            "reportingForm": {
                "reportingForm": "",
                "reason": "",
                "formSubmissionFormPlaceholder": ""
            },
            "selectedTable": {
                "tableNameInChinesePlaceholder": "",
                "tableNameInPortuguesePlaceholder": "",
                "selectACategoryFirst": ""
            }
        }
    },
    "task_web_catalog_approval": {
        "titleName": "",
        "internalFinancialInstitutions": "Organismo criado em termos financeiros",
        "internalFinancialInstitutionsPlaceholder": "Organismo criado em termos financeiros"
    },
    "task_web_task_search_issue": {
        "titleName": "",
        "stampSituation": "",
        "signatureStatus": "",
        "validityOfSignedWorkOrder": "",
        "effective": "",
        "invalid": "Caducado",
        "abandonSignature": "",
        "auditStatus": "",
        "tips": "",
        "startReportingTime": "",
        "fillingDeadline": "",
        "fillingDate": ""
    },
    "task_web_catalog_report": {
        "titleName": ""
    },
    "task_web_task_search_fill": {
        "titleName": ""
    }
}